snippetlib/__init__.py
snippetlib/menu.py
snippetlib/paste_snippet.py
snippetlib/upload_snippet.py
snippetlib/.ipynb_checkpoints/__init__-checkpoint.py
snippetlib/menu/KD-Snippets/Base imports.py
snippetlib/menu/KD-Snippets/How to create new snippets.py
snippetlib/menu/KD-Snippets/How to upload your snippets.py
snippetlib/menu/KD-Snippets/Data/Documentation Pandas
snippetlib/menu/KD-Snippets/Data/Read/Read csv.py
snippetlib/menu/KD-Snippets/Data/Read/Read pickle.py
snippetlib/menu/KD-Snippets/Data/Read/Example Data/California housing.py
snippetlib/menu/KD-Snippets/Data/Read/Example Data/Diabetes.py
snippetlib/menu/KD-Snippets/Data/Read/Example Data/Double pendulum.py
snippetlib/menu/KD-Snippets/Data/Read/Example Data/Earthquakes.py
snippetlib/menu/KD-Snippets/Data/Read/Example Data/Iris.py
snippetlib/menu/KD-Snippets/Data/Read/Example Data/Stock data.py
snippetlib/menu/KD-Snippets/Data/Transform/Apply function to attribute.py
snippetlib/menu/KD-Snippets/Data/Transform/Merge on same key.py
snippetlib/menu/KD-Snippets/Data/Transform/Scale and Normalize.py
snippetlib/menu/KD-Snippets/Data/Transform/Select only numeric attributes.py
snippetlib/menu/KD-Snippets/Data/Transform/Set timestamp as index.py
snippetlib/menu/KD-Snippets/Data/Transform/Split into binary attributes.py
snippetlib/menu/KD-Snippets/Data/Write/Write pickle.py
snippetlib/menu/KD-Snippets/Data/Write/Write to csv.py
snippetlib/menu/KD-Snippets/Modelling/Documentation Scikit Learn
snippetlib/menu/KD-Snippets/Modelling/Classification/Decision Tree.py
snippetlib/menu/KD-Snippets/Modelling/Classification/Documentation
snippetlib/menu/KD-Snippets/Modelling/Classification/Gradient Boosting.py
snippetlib/menu/KD-Snippets/Modelling/Classification/KNN-CLassifier.py
snippetlib/menu/KD-Snippets/Modelling/Classification/Logistic Regression.py
snippetlib/menu/KD-Snippets/Modelling/Classification/SVM.py
snippetlib/menu/KD-Snippets/Modelling/Clustering/DB-Scan clustering.py
snippetlib-1.4.dist-info/LICENSE
snippetlib-1.4.dist-info/METADATA
snippetlib-1.4.dist-info/WHEEL
snippetlib-1.4.dist-info/top_level.txt
snippetlib-1.4.dist-info/RECORD
