Metadata-Version: 2.1
Name: snippetlib
Version: 1.4
Summary: Jupyter Notebook Menu Extension.
Home-page: https://github.com/fraunhofer-iais/IAIS-Jupyter-Snippets-Extension
Author: 
Author-email: 
License: UNKNOWN
Platform: UNKNOWN
Classifier: Development Status :: 5 - Production/Stable
Classifier: Intended Audience :: Developers
Classifier: Topic :: Software Development :: Build Tools
Classifier: License :: OSI Approved :: MIT License
Classifier: Programming Language :: Python :: 3
Classifier: Programming Language :: Python :: 3.4
Classifier: Programming Language :: Python :: 3.5
Classifier: Programming Language :: Python :: 3.6
Requires-Dist: ipywidgets (<=7.5.1)
